stairval/__init__.py
stairval/_api.py
stairval/_auditor.py
stairval/py.typed
stairval/notepad/__init__.py
stairval/notepad/_api.py
stairval/notepad/_config.py
stairval/notepad/_test_tree.py
stairval/notepad/_tree.py
stairval-0.2.4.dist-info/licenses/LICENSE
stairval-0.2.4.dist-info/METADATA
stairval-0.2.4.dist-info/WHEEL
stairval-0.2.4.dist-info/top_level.txt
stairval-0.2.4.dist-info/RECORD
