Metadata-Version: 2.4
Name: stairval
Version: 0.2.4
Summary: Validation framework for hierarchical data structures
Author-email: Daniel Danis <daniel.gordon.danis@protonmail.com>
License:                     GNU GENERAL PUBLIC LICENSE
Project-URL: homepage, https://github.com/ielis/stairval
Project-URL: repository, https://github.com/ielis/stairval.git
Project-URL: documentation, https://github.com/ielis/stairval
Project-URL: bugtracker, https://github.com/ielis/stairval/issues
Keywords: Validation,Data structures
Classifier: Development Status :: 3 - Alpha
Classifier: License :: OSI Approved :: MIT License
Classifier: Operating System :: OS Independent
Classifier: Programming Language :: Python :: 3.9
Classifier: Programming Language :: Python :: 3.10
Classifier: Programming Language :: Python :: 3.11
Classifier: Programming Language :: Python :: 3.12
Classifier: Programming Language :: Python :: 3.13
Requires-Python: >=3.9
License-File: LICENSE
Provides-Extra: test
Requires-Dist: pytest<8.0.0,>=7.0.0; extra == "test"
Requires-Dist: ruff>=0.12.2; extra == "test"
Provides-Extra: docs
Requires-Dist: sphinx>=7.0.0; extra == "docs"
Requires-Dist: sphinx-rtd-theme>=1.3.0; extra == "docs"
Requires-Dist: sphinx-copybutton>=0.5.0; extra == "docs"
Dynamic: license-file
